ptttloggg/__init__.py
ptttloggg/ptttloggg.py
ptttloggg-0.0.3.dist-info/METADATA
ptttloggg-0.0.3.dist-info/RECORD
ptttloggg-0.0.3.dist-info/WHEEL
ptttloggg-0.0.3.dist-info/top_level.txt
