Metadata-Version: 2.1
Name: ptttloggg
Version: 0.0.3
Summary: web_log
Home-page: https://github.com/PtttCode/tornado_Log
Author: pangtong
Author-email: tongpang@webot.com
License: MIT
Keywords: log,easy
Platform: any
